examples/cf_clearance.py
examples/recaptcha-v2.py
solvium/__init__.py
solvium/client.py
solvium-1.0.1.dist-info/licenses/LICENSE
solvium-1.0.1.dist-info/METADATA
solvium-1.0.1.dist-info/WHEEL
solvium-1.0.1.dist-info/top_level.txt
solvium-1.0.1.dist-info/RECORD
