Metadata-Version: 2.4
Name: solvium
Version: 1.0.1
Summary: Python SDK for Solvium
Project-URL: Homepage, https://github.com/solvium-captcha/python-lib
Project-URL: Repository, https://github.com/solvium-captcha/python-lib
Project-URL: Documentation, https://docs.solvium.io/getting-started
Keywords: captcha,turnstile,recaptcha,cloudflare,vercel,bot-detection,automation,web-scraping,solvium
Classifier: Development Status :: 5 - Production/Stable
Classifier: Intended Audience :: Developers
Classifier: Operating System :: OS Independent
Classifier: Programming Language :: Python :: 3
Classifier: Programming Language :: Python :: 3.8
Classifier: Programming Language :: Python :: 3.9
Classifier: Programming Language :: Python :: 3.10
Classifier: Programming Language :: Python :: 3.11
Classifier: Programming Language :: Python :: 3.12
Classifier: Topic :: Internet :: WWW/HTTP
Classifier: Topic :: Software Development :: Libraries :: Python Modules
Classifier: Topic :: Security
Requires-Python: >=3.8
License-File: LICENSE
Requires-Dist: httpx>=0.24.0
Requires-Dist: loguru>=0.6.0
Dynamic: license-file
